cgi_tools/__init__.py
cgi_tools/http_responses.py
cgi_tools/params.py
cgi_tools/system.py
cgi_tools/types.py
cgi_tools/validators.py
cgi_tools/version.py
cgi_tools-0.0.4.data/scripts/jinja2-cgi
cgi_tools-0.0.4.dist-info/METADATA
cgi_tools-0.0.4.dist-info/WHEEL
cgi_tools-0.0.4.dist-info/top_level.txt
cgi_tools-0.0.4.dist-info/RECORD
