Metadata-Version: 2.1
Name: cgi-tools
Version: 0.0.4
Summary: Collection of tools for quick CGI scripts development
Home-page: https://github.com/agordon/cgi-tools
Author: Assaf Gordon
Author-email: AssafGordon@gmail.com
License: BSD
Keywords: CGI
Platform: UNKNOWN
Classifier: Development Status :: 3 - Alpha
Classifier: License :: OSI Approved :: BSD License
Classifier: Topic :: Internet :: WWW/HTTP :: Dynamic Content :: CGI Tools/Libraries
Classifier: Topic :: Software Development :: Libraries :: Python Modules
Requires-Dist: jinja2
Requires-Dist: werkzeug
